pymacroms/__init__.py
pymacroms/database.py
pymacroms/helper_functions.py
pymacroms/import_spectrum.py
pymacroms/polymer.py
pymacroms/single_molecule.py
pymacroms/spectrum_processing.py
pymacroms/RawFileReader/Unix/RawFileReaderLicense.txt
pymacroms/RawFileReader/Unix/ThermoFisher.CommonCore.BackgroundSubtraction.dll
pymacroms/RawFileReader/Unix/ThermoFisher.CommonCore.Data.dll
pymacroms/RawFileReader/Unix/ThermoFisher.CommonCore.MassPrecisionEstimator.dll
pymacroms/RawFileReader/Unix/ThermoFisher.CommonCore.RawFileReader.dll
pymacroms/RawFileReader/Windows/RawFileReaderLicense.txt
pymacroms/RawFileReader/Windows/ThermoFisher.CommonCore.BackgroundSubtraction.dll
pymacroms/RawFileReader/Windows/ThermoFisher.CommonCore.Data.dll
pymacroms/RawFileReader/Windows/ThermoFisher.CommonCore.MassPrecisionEstimator.dll
pymacroms/RawFileReader/Windows/ThermoFisher.CommonCore.RawFileReader.dll
pymacroms-1.1.7.dist-info/LICENSE
pymacroms-1.1.7.dist-info/METADATA
pymacroms-1.1.7.dist-info/WHEEL
pymacroms-1.1.7.dist-info/top_level.txt
pymacroms-1.1.7.dist-info/RECORD
