Metadata-Version: 2.1
Name: pymacroms
Version: 1.1.7
Summary: pyMacroMS - High performance quantification of complex high resolution polymer mass spectra
Home-page: http://macroarc.org/research/macroarc-pyMacroMS.html
Author: Kevin De Bruycker and Tim Krappitz
Author-email: kevindebruycker@gmail.com
License: MIT License
Platform: UNKNOWN
Classifier: Programming Language :: Python :: 3
Classifier: Programming Language :: Python :: 3.7
Classifier: Programming Language :: Python :: 3.8
Classifier: License :: OSI Approved :: MIT License
Classifier: Operating System :: OS Independent
Requires-Dist: IsoSpecPy (>=2)
Requires-Dist: matplotlib
Requires-Dist: numpy
Requires-Dist: pandas
Requires-Dist: progressbar2
Requires-Dist: PySimpleGUI
Requires-Dist: pythonnet
Requires-Dist: reportlab
Requires-Dist: sklearn
Requires-Dist: svglib (>=0.9.0)
